redfearn.py
tests.py
redfearn-1.0.4.dist-info/DESCRIPTION.rst
redfearn-1.0.4.dist-info/METADATA
redfearn-1.0.4.dist-info/RECORD
redfearn-1.0.4.dist-info/WHEEL
redfearn-1.0.4.dist-info/metadata.json
redfearn-1.0.4.dist-info/top_level.txt
