Metadata-Version: 2.0
Name: redfearn
Version: 1.0.4
Summary: Converts between latitude/longitude and grid coordinates using Redfearn's Formula
Home-page: http://plaintech.net.au/redfearn
Author: PHil Howarth
Author-email: phil@plaintech.net.au
License: GPLv3+
Keywords: conversion,GDA,MGA,latitude,longitude
Platform: UNKNOWN
Classifier: Programming Language :: Python
Classifier: Programming Language :: Python :: 3
Classifier: Development Status :: 4 - Beta
Classifier: Environment :: Other Environment
Classifier: Intended Audience :: Developers
Classifier: Intended Audience :: Science/Research
Classifier: License :: OSI Approved :: GNU General Public License v3 or later (GPLv3+)
Classifier: Natural Language :: English
Classifier: Operating System :: OS Independent
Classifier: Topic :: Software Development :: Libraries :: Python Modules
Classifier: Topic :: Scientific/Engineering :: GIS
